scETM/__init__.py
scETM/batch_sampler.py
scETM/eval_utils.py
scETM/logging_utils.py
scETM/trainer.py
scETM/model/BaseCellModel.py
scETM/model/__init__.py
scETM/model/model_utils.py
scETM/model/scETM.py
scETM/models/BaseCellModel.py
scETM/models/BatchClassifier.py
scETM/models/__init__.py
scETM/models/model_utils.py
scETM/models/scETM.py
scETM/models/scVI.py
scETM/trainers/BatchAdversarialTrainer.py
scETM/trainers/MMDTrainer.py
scETM/trainers/UnsupervisedTrainer.py
scETM/trainers/__init__.py
scETM/trainers/trainer_utils.py
scETM-0.5.0.dist-info/LICENSE
scETM-0.5.0.dist-info/METADATA
scETM-0.5.0.dist-info/WHEEL
scETM-0.5.0.dist-info/top_level.txt
scETM-0.5.0.dist-info/RECORD
