Metadata-Version: 2.1
Name: scETM
Version: 0.5.0
Summary: Single cell embedded topic model for integrated scRNA-seq data analysis.
Home-page: https://github.com/hui2000ji/scETM/
Author: Huiyu Cai, Yifan Zhao, Yue Li
Author-email: hy_cai@pku.edu.cn
License: BSD 3-Clause License
Project-URL: Bug Tracker, https://github.com/hui2000ji/scETM/issues
Platform: UNKNOWN
Classifier: Programming Language :: Python :: 3
Classifier: License :: OSI Approved :: BSD License
Classifier: Operating System :: MacOS :: MacOS X
Classifier: Operating System :: Microsoft :: Windows
Classifier: Operating System :: POSIX :: Linux
Requires-Python: >=3.6
License-File: LICENSE
Requires-Dist: torch (>=1.5)
Requires-Dist: numpy (>=1.16.2)
Requires-Dist: matplotlib (>=3.1.2)
Requires-Dist: scikit-learn (>=0.20.3)
Requires-Dist: h5py (>=2.9.0)
Requires-Dist: pandas (>=0.25)
Requires-Dist: tqdm (>=4.31.1)
Requires-Dist: anndata (>=0.7)
Requires-Dist: scanpy (>=1.4.6)
Requires-Dist: scipy (>=1.0)
Requires-Dist: louvain (>=0.6.1)
Requires-Dist: leidenalg (>=0.7.0)
Requires-Dist: psutil
